[{"message":"feat(alt-report): markdown + HTML attachments, merged HTTP step, assertion polish","author":"Karol Wojcik","timestamp":1776326686000,"run":"609","status":"completed","sha":"146eab99dd4ca2646b9ac50804f74901b319c9dc","repo_url":"https:\/\/github.com\/Blockether\/spel","version":"v0.9.5-candidate","tests":{"passed":2311,"failed":0,"broken":0,"skipped":0,"total":2311},"run_url":"https:\/\/github.com\/Blockether\/spel\/actions\/runs\/24499212597","passed":true,"badge":"candidate"},{"message":"feat(alt-report): merge HTTP step + body, live iframe for HTML attachments","author":"Karol Wojcik","timestamp":1776255753000,"run":"608","status":"completed","sha":"a9a2db025a757af4a216d1a24c0f3dbfa6553fdb","repo_url":"https:\/\/github.com\/Blockether\/spel","version":"v0.9.5-candidate","tests":{"total":2311,"failed":0,"broken":0,"skipped":0,"passed":2311},"run_url":"https:\/\/github.com\/Blockether\/spel\/actions\/runs\/24454241759","passed":true,"badge":"candidate"},{"message":"refactor(alt-report): soften green for passed \u2014 outline only, no bg tint","author":"Karol Wojcik","timestamp":1776249463000,"run":"607","status":"completed","sha":"577f2be6197f3bf628f5307c09eaf576bb959e5e","repo_url":"https:\/\/github.com\/Blockether\/spel","version":"v0.9.4-candidate","tests":{"total":2311,"failed":0,"broken":0,"skipped":0,"passed":2311},"run_url":"https:\/\/github.com\/Blockether\/spel\/actions\/runs\/24449898061","passed":true,"badge":"candidate"},{"message":"feat(alt-report): tighten failure UX \u2014 full trace, per-step errors, no dupe","author":"Karol Wojcik","timestamp":1776249019000,"run":"606","status":"completed","sha":"e682bccf053005e23d4adb5753de619e58fa9df9","repo_url":"https:\/\/github.com\/Blockether\/spel","version":"v0.9.4-candidate","tests":{"total":2311,"failed":0,"broken":0,"skipped":0,"passed":2311},"run_url":"https:\/\/github.com\/Blockether\/spel\/actions\/runs\/24449596475","passed":true,"badge":"candidate"},{"message":"test(alt-report): add second result in toolbar tests to leave single mode","author":"Karol Wojcik","timestamp":1776172038000,"run":"605","status":"completed","sha":"5a52da6fce13df42ca02419a2681f7b5bcab09d3","repo_url":"https:\/\/github.com\/Blockether\/spel","version":"v0.9.3-candidate","tests":{"total":2311,"failed":0,"broken":0,"skipped":0,"passed":2311},"run_url":"https:\/\/github.com\/Blockether\/spel\/actions\/runs\/24400669072","passed":true,"badge":"candidate"},{"message":"feat(alt-report): polish single-test mode + rich-headers showcase test","author":"Karol Wojcik","timestamp":1776170159000,"run":"604","status":"completed","sha":"580ef3021da5adf863535ce822678f40a91dd276","repo_url":"https:\/\/github.com\/Blockether\/spel","version":"v0.9.3-candidate","tests":{"total":2313,"failed":2,"broken":0,"skipped":0,"passed":2311},"run_url":"https:\/\/github.com\/Blockether\/spel\/actions\/runs\/24399238569","passed":false,"badge":"candidate"},{"message":"fix(test): normalize CRLF in sci_eval stdout assertions for Windows","author":"Karol Wojcik","timestamp":1776085113000,"run":"603","status":"completed","sha":"8af00b49a439cbaf49014aa89acbe2c4bac87c25","repo_url":"https:\/\/github.com\/Blockether\/spel","version":"v0.9.2-candidate","tests":{"total":2310,"failed":0,"broken":0,"skipped":0,"passed":2310},"run_url":"https:\/\/github.com\/Blockether\/spel\/actions\/runs\/24344648231","passed":true,"badge":"candidate"},{"message":"feat(sci): full math class surface \u2014 Math, StrictMath, MathContext, RoundingMode, Random family","author":"Karol Wojcik","timestamp":1776084257000,"run":"602","status":"completed","sha":"7628b5898150c267d1ffc12f97522cfd3e9a2e7e","repo_url":"https:\/\/github.com\/Blockether\/spel","version":"v0.9.2-candidate","tests":{"total":2310,"failed":0,"broken":0,"skipped":0,"passed":2310},"run_url":"https:\/\/github.com\/Blockether\/spel\/actions\/runs\/24344020611","passed":false,"badge":"candidate"},{"message":"test(sci_eval): pin println + result contract (issue #106)","author":"Karol Wojcik","timestamp":1776081890000,"run":"601","status":"completed","sha":"796f1ce900c3cc0db6344cdf785b756842abd9ea","repo_url":"https:\/\/github.com\/Blockether\/spel","version":"v0.9.2-candidate","tests":{"total":2304,"failed":0,"broken":0,"skipped":0,"passed":2304},"run_url":"https:\/\/github.com\/Blockether\/spel\/actions\/runs\/24342383699","passed":false,"badge":"candidate"},{"message":"refactor(report): rename \"block\" alternative report to \"alternative\"","author":"Karol Wojcik","timestamp":1776068998000,"run":"600","status":"completed","sha":"d8ffab96fa40a8c73e5d0ac0027f68fc7f419b20","repo_url":"https:\/\/github.com\/Blockether\/spel","version":"v0.9.1-candidate","tests":{"total":2292,"failed":0,"broken":0,"skipped":0,"passed":2292},"run_url":"https:\/\/github.com\/Blockether\/spel\/actions\/runs\/24333572772","passed":true,"badge":"candidate"},{"message":"feat(page,sci): evaluate-file, add-init-script!, new-cdp-session","author":"Karol Wojcik","timestamp":1776048264000,"run":"599","status":"completed","sha":"e34cbeaa9e162c89bbae4b59e9d32708ca10562d","repo_url":"https:\/\/github.com\/Blockether\/spel","version":"v0.8.1-candidate","tests":{"total":2292,"failed":0,"broken":0,"skipped":0,"passed":2292},"run_url":"https:\/\/github.com\/Blockether\/spel\/actions\/runs\/24323245375","passed":true,"badge":"candidate"},{"message":"fix(sci): restore pprint\/pp\/clojure.pprint \u2014 all backed by zprint","author":"Karol Wojcik","timestamp":1776046568000,"run":"598","status":"completed","sha":"aa2377b52639160f10ea0a90111260002ae98988","repo_url":"https:\/\/github.com\/Blockether\/spel","version":"v0.8.1-candidate","tests":{"total":2286,"failed":0,"broken":0,"skipped":0,"passed":2286},"run_url":"https:\/\/github.com\/Blockether\/spel\/actions\/runs\/24322590593","passed":true,"badge":"candidate"},{"message":"fix(ci): restore 3 orchestrator sentinel strings removed by compression","author":"Karol Wojcik","timestamp":1776036198000,"run":"597","status":"completed","sha":"340f13f93d60396166d19453ba5f3fd44962080e","repo_url":"https:\/\/github.com\/Blockether\/spel","version":"v0.7.12-candidate","tests":{"total":2287,"failed":0,"broken":0,"skipped":0,"passed":2287},"run_url":"https:\/\/github.com\/Blockether\/spel\/actions\/runs\/24318895749","passed":true,"badge":"candidate"},{"message":"fix(evals): restore canonical contract strings lost in caveman compression","author":"Karol Wojcik","timestamp":1776034931000,"run":"596","status":"completed","sha":"ef10f6c2bc8785d16266b9508c7cfccf9acd23b1","repo_url":"https:\/\/github.com\/Blockether\/spel","version":"v0.7.12-candidate","tests":{"total":2287,"failed":0,"broken":0,"skipped":0,"passed":2287},"run_url":"https:\/\/github.com\/Blockether\/spel\/actions\/runs\/24318513853","passed":false,"badge":"candidate"},{"message":"fix(ci): sync tests + docs with spel-test-planner removal, silence boxed math","author":"Karol Wojcik","timestamp":1776030854000,"run":"595","status":"completed","sha":"f25a9c148c70c52f354b7d07b4ae2353018804c9","repo_url":"https:\/\/github.com\/Blockether\/spel","version":"v0.7.12-candidate","tests":{"total":2287,"failed":0,"broken":0,"skipped":0,"passed":2287},"run_url":"https:\/\/github.com\/Blockether\/spel\/actions\/runs\/24317302314","passed":false,"badge":"candidate"}]