{"name":"#500 · d837aaeb2b29c053068fb742d33cb0f88faa8ba3 · Michał Kruk · fix(allure): always use resolved full URL in HTTP exchange attachments","stats":{"total":23,"passed":23},"status":"passed","duration":10884,"createdAt":1773830110063,"plugin":"Awesome","newTests":[],"flakyTests":[],"retryTests":[],"meta":{"reportId":"b3c5ced5-a9eb-46a5-a2f3-691fc6efcef4","singleFile":false,"withTestResultsLinks":true},"pullRequestHref":"","jobHref":"https://github.com/Blockether/spel/actions/runs/23240834758"}