{"stats":{"total":2233,"passed":2233},"status":"passed","newTests":[],"flakyTests":[],"retryTests":[],"name":"#553 · 9b1ddb3da982c28431930270f1b9b81c0f6b693c · Michał Kruk · fix: update CLI bash test assertions for redesigned alternative report","duration":165907,"createdAt":1775900217276,"plugin":"Awesome","meta":{"reportId":"c7ff29b3-1328-4672-bd83-a9dccdf5c34a","singleFile":false,"withTestResultsLinks":true},"pullRequestHref":"","jobHref":"https://github.com/Blockether/spel/actions/runs/24280026730"}